pywhy_stats/__init__.py
pywhy_stats/_version.py
pywhy_stats/api.py
pywhy_stats/conditional_ksample/__init__.py
pywhy_stats/conditional_ksample/base_propensity.py
pywhy_stats/conditional_ksample/bregman.py
pywhy_stats/conditional_ksample/kcd.py
pywhy_stats/independence/__init__.py
pywhy_stats/independence/fisherz.py
pywhy_stats/independence/kci.py
pywhy_stats/independence/power_divergence.py
pywhy_stats/kernel_utils.py
pywhy_stats/kernels.py
pywhy_stats/pvalue_result.py
pywhy_stats/utils.py
pywhy_stats-0.1.dist-info/LICENSE
pywhy_stats-0.1.dist-info/METADATA
pywhy_stats-0.1.dist-info/WHEEL
pywhy_stats-0.1.dist-info/RECORD
