Metadata-Version: 2.1
Name: pywhy-stats
Version: 0.1
Summary: Statistical methods for Python
Home-page: https://github.com/pywhy/pywhy-stats
License: MIT
Keywords: independence testing,causal statistics,conditional independence
Author: PyWhy Community
Author-email: bloebp@amazon.com
Requires-Python: >=3.8,<3.11
Classifier: Development Status :: 4 - Beta
Classifier: License :: OSI Approved :: MIT License
Classifier: Programming Language :: Python :: 3
Classifier: Programming Language :: Python :: 3.8
Classifier: Programming Language :: Python :: 3.9
Classifier: Programming Language :: Python :: 3.10
Requires-Dist: numpy (>=1.23.0,<2.0.0)
Requires-Dist: scikit-learn (>=1.0)
Requires-Dist: scipy (>=1.9.0,<2.0.0)
Project-URL: Documentation, https://py-why.github.io/pywhy-stats
Project-URL: Repository, https://github.com/pywhy/pywhy-stats
